sqlpress/Database.py
sqlpress/Table.py
sqlpress/__init__.py
sqlpress-2020.11.12.dist-info/METADATA
sqlpress-2020.11.12.dist-info/WHEEL
sqlpress-2020.11.12.dist-info/top_level.txt
sqlpress-2020.11.12.dist-info/RECORD
